dataliner/__init__.py
dataliner/preprocessing.py
dataliner/datasets/titanic_test.csv
dataliner/datasets/titanic_train.csv
dataliner-1.3.1.dist-info/METADATA
dataliner-1.3.1.dist-info/WHEEL
dataliner-1.3.1.dist-info/top_level.txt
dataliner-1.3.1.dist-info/RECORD
